rulengine/__init__.py
rulengine/conditions.py
rulengine/core.py
rulengine-0.0.6.dist-info/DESCRIPTION.rst
rulengine-0.0.6.dist-info/METADATA
rulengine-0.0.6.dist-info/metadata.json
rulengine-0.0.6.dist-info/RECORD
rulengine-0.0.6.dist-info/top_level.txt
rulengine-0.0.6.dist-info/WHEEL
