Metadata-Version: 2.0
Name: rulengine
Version: 0.0.6
Summary: Simple Rule Engine
Home-page: https://github.com/baranbartu/rulengine
Author: Baran Bartu Demirci
Author-email: bbartu.demirci@gmail.com
License: MIT
Download-URL: https://github.com/baranbartu/rulengine/tarball/0.0.6
Keywords: python,rule,rule executor,rule engine
Platform: UNKNOWN
